<annotation>
	<folder>Bear</folder>
	<filename>23c053b86ed08160.jpg</filename>
	<path>23c053b86ed08160.jpg</path>
	<source>
		<database>Unknown</database>
	</source>
	<size>
		<width>512</width>
		<height>512</height>
		<depth>3</depth>
	</size>
	<segmented>0</segmented>
	<object>
		<name>hand</name>
		<pose>Unspecified</pose>
		<truncated>0</truncated>
		<difficult>0</difficult>
		<bndbox>
			<xmin>330</xmin>
			<ymin>299</ymin>
			<xmax>399</xmax>
			<ymax>376</ymax>
		</bndbox>
	</object>
	<object>
		<name>hand</name>
		<pose>Unspecified</pose>
		<truncated>0</truncated>
		<difficult>0</difficult>
		<bndbox>
			<xmin>0</xmin>
			<ymin>313</ymin>
			<xmax>59</xmax>
			<ymax>366</ymax>
		</bndbox>
	</object>
	<object>
		<name>hand</name>
		<pose>Unspecified</pose>
		<truncated>0</truncated>
		<difficult>0</difficult>
		<bndbox>
			<xmin>226</xmin>
			<ymin>361</ymin>
			<xmax>268</xmax>
			<ymax>396</ymax>
		</bndbox>
	</object>
</annotation>