<annotation>
	<folder>Bear</folder>
	<filename>2ab0cac6cfb57c02.jpg</filename>
	<path>2ab0cac6cfb57c02.jpg</path>
	<source>
		<database>Unknown</database>
	</source>
	<size>
		<width>512</width>
		<height>512</height>
		<depth>3</depth>
	</size>
	<segmented>0</segmented>
	<object>
		<name>hand</name>
		<pose>Unspecified</pose>
		<truncated>0</truncated>
		<difficult>0</difficult>
		<bndbox>
			<xmin>125</xmin>
			<ymin>382</ymin>
			<xmax>236</xmax>
			<ymax>508</ymax>
		</bndbox>
	</object>
	<object>
		<name>hand</name>
		<pose>Unspecified</pose>
		<truncated>0</truncated>
		<difficult>0</difficult>
		<bndbox>
			<xmin>153</xmin>
			<ymin>296</ymin>
			<xmax>206</xmax>
			<ymax>359</ymax>
		</bndbox>
	</object>
	<object>
		<name>hand</name>
		<pose>Unspecified</pose>
		<truncated>0</truncated>
		<difficult>0</difficult>
		<bndbox>
			<xmin>264</xmin>
			<ymin>306</ymin>
			<xmax>346</xmax>
			<ymax>359</ymax>
		</bndbox>
	</object>
	<object>
		<name>hand</name>
		<pose>Unspecified</pose>
		<truncated>0</truncated>
		<difficult>0</difficult>
		<bndbox>
			<xmin>272</xmin>
			<ymin>335</ymin>
			<xmax>340</xmax>
			<ymax>385</ymax>
		</bndbox>
	</object>
</annotation>