<annotation>
	<folder>Bear</folder>
	<filename>36e127bd3b005aa6.jpg</filename>
	<path>36e127bd3b005aa6.jpg</path>
	<source>
		<database>Unknown</database>
	</source>
	<size>
		<width>512</width>
		<height>512</height>
		<depth>3</depth>
	</size>
	<segmented>0</segmented>
	<object>
		<name>hand</name>
		<pose>Unspecified</pose>
		<truncated>0</truncated>
		<difficult>0</difficult>
		<bndbox>
			<xmin>388</xmin>
			<ymin>234</ymin>
			<xmax>420</xmax>
			<ymax>336</ymax>
		</bndbox>
	</object>
</annotation>