<annotation>
	<folder>Bear</folder>
	<filename>38ab8088d2c1508a.jpg</filename>
	<path>38ab8088d2c1508a.jpg</path>
	<source>
		<database>Unknown</database>
	</source>
	<size>
		<width>512</width>
		<height>512</height>
		<depth>3</depth>
	</size>
	<segmented>0</segmented>
	<object>
		<name>hand</name>
		<pose>Unspecified</pose>
		<truncated>0</truncated>
		<difficult>0</difficult>
		<bndbox>
			<xmin>423</xmin>
			<ymin>341</ymin>
			<xmax>489</xmax>
			<ymax>399</ymax>
		</bndbox>
	</object>
	<object>
		<name>hand</name>
		<pose>Unspecified</pose>
		<truncated>0</truncated>
		<difficult>0</difficult>
		<bndbox>
			<xmin>242</xmin>
			<ymin>267</ymin>
			<xmax>327</xmax>
			<ymax>424</ymax>
		</bndbox>
	</object>
	<object>
		<name>hand</name>
		<pose>Unspecified</pose>
		<truncated>0</truncated>
		<difficult>0</difficult>
		<bndbox>
			<xmin>407</xmin>
			<ymin>402</ymin>
			<xmax>465</xmax>
			<ymax>464</ymax>
		</bndbox>
	</object>
</annotation>