<annotation>
	<folder>Bear</folder>
	<filename>3c6a174cbf5ceb54.jpg</filename>
	<path>3c6a174cbf5ceb54.jpg</path>
	<source>
		<database>Unknown</database>
	</source>
	<size>
		<width>512</width>
		<height>512</height>
		<depth>3</depth>
	</size>
	<segmented>0</segmented>
	<object>
		<name>hand</name>
		<pose>Unspecified</pose>
		<truncated>0</truncated>
		<difficult>0</difficult>
		<bndbox>
			<xmin>145</xmin>
			<ymin>345</ymin>
			<xmax>236</xmax>
			<ymax>415</ymax>
		</bndbox>
	</object>
	<object>
		<name>hand</name>
		<pose>Unspecified</pose>
		<truncated>0</truncated>
		<difficult>0</difficult>
		<bndbox>
			<xmin>238</xmin>
			<ymin>390</ymin>
			<xmax>300</xmax>
			<ymax>487</ymax>
		</bndbox>
	</object>
</annotation>