<annotation>
	<folder>Bear</folder>
	<filename>431493211acbc5ae.jpg</filename>
	<path>431493211acbc5ae.jpg</path>
	<source>
		<database>Unknown</database>
	</source>
	<size>
		<width>512</width>
		<height>512</height>
		<depth>3</depth>
	</size>
	<segmented>0</segmented>
	<object>
		<name>hand</name>
		<pose>Unspecified</pose>
		<truncated>0</truncated>
		<difficult>0</difficult>
		<bndbox>
			<xmin>234</xmin>
			<ymin>200</ymin>
			<xmax>273</xmax>
			<ymax>269</ymax>
		</bndbox>
	</object>
	<object>
		<name>hand</name>
		<pose>Unspecified</pose>
		<truncated>0</truncated>
		<difficult>0</difficult>
		<bndbox>
			<xmin>161</xmin>
			<ymin>189</ymin>
			<xmax>213</xmax>
			<ymax>262</ymax>
		</bndbox>
	</object>
</annotation>