<annotation>
	<folder>Bear</folder>
	<filename>44131ea33cc994b3.jpg</filename>
	<path>44131ea33cc994b3.jpg</path>
	<source>
		<database>Unknown</database>
	</source>
	<size>
		<width>512</width>
		<height>512</height>
		<depth>3</depth>
	</size>
	<segmented>0</segmented>
	<object>
		<name>hand</name>
		<pose>Unspecified</pose>
		<truncated>0</truncated>
		<difficult>0</difficult>
		<bndbox>
			<xmin>250</xmin>
			<ymin>410</ymin>
			<xmax>290</xmax>
			<ymax>454</ymax>
		</bndbox>
	</object>
</annotation>