<annotation>
	<folder>Bear</folder>
	<filename>4439a80b4d4a7c94.jpg</filename>
	<path>4439a80b4d4a7c94.jpg</path>
	<source>
		<database>Unknown</database>
	</source>
	<size>
		<width>512</width>
		<height>512</height>
		<depth>3</depth>
	</size>
	<segmented>0</segmented>
	<object>
		<name>hand</name>
		<pose>Unspecified</pose>
		<truncated>0</truncated>
		<difficult>0</difficult>
		<bndbox>
			<xmin>159</xmin>
			<ymin>204</ymin>
			<xmax>185</xmax>
			<ymax>222</ymax>
		</bndbox>
	</object>
	<object>
		<name>hand</name>
		<pose>Unspecified</pose>
		<truncated>0</truncated>
		<difficult>0</difficult>
		<bndbox>
			<xmin>270</xmin>
			<ymin>20</ymin>
			<xmax>295</xmax>
			<ymax>50</ymax>
		</bndbox>
	</object>
	<object>
		<name>hand</name>
		<pose>Unspecified</pose>
		<truncated>0</truncated>
		<difficult>0</difficult>
		<bndbox>
			<xmin>440</xmin>
			<ymin>270</ymin>
			<xmax>511</xmax>
			<ymax>511</ymax>
		</bndbox>
	</object>
</annotation>