<annotation>
	<folder>Bear</folder>
	<filename>4810e884a345ba06.jpg</filename>
	<path>4810e884a345ba06.jpg</path>
	<source>
		<database>Unknown</database>
	</source>
	<size>
		<width>512</width>
		<height>512</height>
		<depth>3</depth>
	</size>
	<segmented>0</segmented>
	<object>
		<name>hand</name>
		<pose>Unspecified</pose>
		<truncated>0</truncated>
		<difficult>0</difficult>
		<bndbox>
			<xmin>158</xmin>
			<ymin>128</ymin>
			<xmax>234</xmax>
			<ymax>230</ymax>
		</bndbox>
	</object>
	<object>
		<name>hand</name>
		<pose>Unspecified</pose>
		<truncated>0</truncated>
		<difficult>0</difficult>
		<bndbox>
			<xmin>280</xmin>
			<ymin>165</ymin>
			<xmax>336</xmax>
			<ymax>278</ymax>
		</bndbox>
	</object>
</annotation>