<annotation>
	<folder>Bear</folder>
	<filename>4a2a3e40868c496c.jpg</filename>
	<path>4a2a3e40868c496c.jpg</path>
	<source>
		<database>Unknown</database>
	</source>
	<size>
		<width>512</width>
		<height>512</height>
		<depth>3</depth>
	</size>
	<segmented>0</segmented>
	<object>
		<name>hand</name>
		<pose>Unspecified</pose>
		<truncated>0</truncated>
		<difficult>0</difficult>
		<bndbox>
			<xmin>310</xmin>
			<ymin>307</ymin>
			<xmax>377</xmax>
			<ymax>398</ymax>
		</bndbox>
	</object>
	<object>
		<name>hand</name>
		<pose>Unspecified</pose>
		<truncated>0</truncated>
		<difficult>0</difficult>
		<bndbox>
			<xmin>331</xmin>
			<ymin>283</ymin>
			<xmax>387</xmax>
			<ymax>320</ymax>
		</bndbox>
	</object>
	<object>
		<name>hand</name>
		<pose>Unspecified</pose>
		<truncated>0</truncated>
		<difficult>0</difficult>
		<bndbox>
			<xmin>355</xmin>
			<ymin>68</ymin>
			<xmax>389</xmax>
			<ymax>100</ymax>
		</bndbox>
	</object>
</annotation>