<annotation>
	<folder>Bear</folder>
	<filename>6274fd94b0dd9358.jpg</filename>
	<path>6274fd94b0dd9358.jpg</path>
	<source>
		<database>Unknown</database>
	</source>
	<size>
		<width>512</width>
		<height>512</height>
		<depth>3</depth>
	</size>
	<segmented>0</segmented>
	<object>
		<name>hand</name>
		<pose>Unspecified</pose>
		<truncated>0</truncated>
		<difficult>0</difficult>
		<bndbox>
			<xmin>324</xmin>
			<ymin>96</ymin>
			<xmax>427</xmax>
			<ymax>183</ymax>
		</bndbox>
	</object>
	<object>
		<name>hand</name>
		<pose>Unspecified</pose>
		<truncated>0</truncated>
		<difficult>0</difficult>
		<bndbox>
			<xmin>71</xmin>
			<ymin>117</ymin>
			<xmax>171</xmax>
			<ymax>216</ymax>
		</bndbox>
	</object>
</annotation>