<annotation>
	<folder>Bear</folder>
	<filename>6da6e514cdc8f3dc.jpg</filename>
	<path>6da6e514cdc8f3dc.jpg</path>
	<source>
		<database>Unknown</database>
	</source>
	<size>
		<width>512</width>
		<height>512</height>
		<depth>3</depth>
	</size>
	<segmented>0</segmented>
	<object>
		<name>hand</name>
		<pose>Unspecified</pose>
		<truncated>0</truncated>
		<difficult>0</difficult>
		<bndbox>
			<xmin>0</xmin>
			<ymin>176</ymin>
			<xmax>199</xmax>
			<ymax>493</ymax>
		</bndbox>
	</object>
</annotation>