<annotation>
	<folder>Bear</folder>
	<filename>7474fbf9f0f63d58.jpg</filename>
	<path>7474fbf9f0f63d58.jpg</path>
	<source>
		<database>Unknown</database>
	</source>
	<size>
		<width>512</width>
		<height>512</height>
		<depth>3</depth>
	</size>
	<segmented>0</segmented>
	<object>
		<name>hand</name>
		<pose>Unspecified</pose>
		<truncated>0</truncated>
		<difficult>0</difficult>
		<bndbox>
			<xmin>179</xmin>
			<ymin>333</ymin>
			<xmax>253</xmax>
			<ymax>428</ymax>
		</bndbox>
	</object>
	<object>
		<name>hand</name>
		<pose>Unspecified</pose>
		<truncated>0</truncated>
		<difficult>0</difficult>
		<bndbox>
			<xmin>327</xmin>
			<ymin>366</ymin>
			<xmax>380</xmax>
			<ymax>458</ymax>
		</bndbox>
	</object>
	<object>
		<name>hand</name>
		<pose>Unspecified</pose>
		<truncated>0</truncated>
		<difficult>0</difficult>
		<bndbox>
			<xmin>332</xmin>
			<ymin>194</ymin>
			<xmax>357</xmax>
			<ymax>212</ymax>
		</bndbox>
	</object>
</annotation>